lua/__init__.py
lua/python-lua.7
lua_wrapper-0.6.dist-info/METADATA
lua_wrapper-0.6.dist-info/WHEEL
lua_wrapper-0.6.dist-info/copyright
lua_wrapper-0.6.dist-info/top_level.txt
lua_wrapper-0.6.dist-info/RECORD
