Metadata-Version: 2.1
Name: lua-wrapper
Version: 0.6
Summary: module for using Lua in Python programs
Home-page: https://github.com/wijnen/python-lua
Author: Bas Wijnen
Author-email: wijnen@debian.org
License: AGPL3+
Project-URL: Bug Tracker, https://github.com/wijnen/python-lua/issues
Classifier: Programming Language :: Python :: 3
Classifier: License :: OSI Approved :: GNU Affero General Public License v3 or later (AGPLv3+)
Classifier: Intended Audience :: Developers
Classifier: Development Status :: 4 - Beta
Classifier: Operating System :: OS Independent
Requires-Python: >=3
License-File: debian/copyright
